yaml_tags/__init__.py
yaml_tags/base.py
yaml_tags/inc.py
yaml_tags-0.0.2.dist-info/DESCRIPTION.rst
yaml_tags-0.0.2.dist-info/METADATA
yaml_tags-0.0.2.dist-info/RECORD
yaml_tags-0.0.2.dist-info/WHEEL
yaml_tags-0.0.2.dist-info/metadata.json
yaml_tags-0.0.2.dist-info/top_level.txt
