Metadata-Version: 2.0
Name: yaml-tags
Version: 0.0.2
Summary: 基于 pyyaml，提供一些辅助的 tag
Home-page: https://github.com/anjianshi/yaml_tags
Author: anjianshi
Author-email: anjianshi@gmail.com
License: MIT
Keywords: yaml
Platform: any
Classifier: Intended Audience :: Developers
Classifier: License :: OSI Approved :: MIT License
Classifier: Operating System :: OS Independent
Classifier: Programming Language :: Python
Classifier: Programming Language :: Python :: 3.4
Requires-Dist: pyyaml
